MANIFEST.in
setup.cfg
setup.py
pysapp/__init__.py
pysapp/applications.py
pysapp/base.py
pysapp/commands.py
pysapp/exc.py
pysapp/forms.py
pysapp/middleware.py
pysapp/settings.py
pysapp/site_settings.py.tpl
pysapp/testing.py
pysapp/utils.py
pysapp.egg-info/PKG-INFO
pysapp.egg-info/SOURCES.txt
pysapp.egg-info/dependency_links.txt
pysapp.egg-info/entry_points.txt
pysapp.egg-info/not-zip-safe
pysapp.egg-info/requires.txt
pysapp.egg-info/top_level.txt
pysapp/lib/__init__.py
pysapp/lib/db.py
pysapp/lib/paster_tpl.py
pysapp/lib/paster_tpls/module/__init__.py
pysapp/lib/paster_tpls/module/actions.py
pysapp/lib/paster_tpls/module/commands.py
pysapp/lib/paster_tpls/module/forms.py
pysapp/lib/paster_tpls/module/settings.py_tmpl
pysapp/lib/paster_tpls/module/utils.py
pysapp/lib/paster_tpls/module/views.py
pysapp/lib/paster_tpls/module/model/__init__.py
pysapp/lib/paster_tpls/module/model/metadata.py
pysapp/lib/paster_tpls/module/model/orm.py
pysapp/lib/paster_tpls/module/templates/Index.html_tmpl
pysapp/lib/paster_tpls/project/MANIFEST.in_tmpl
pysapp/lib/paster_tpls/project/notes.txt
pysapp/lib/paster_tpls/project/setup.cfg
pysapp/lib/paster_tpls/project/setup.py_tmpl
pysapp/lib/paster_tpls/project/+package+/__init__.py
pysapp/lib/paster_tpls/project/+package+/applications.py
pysapp/lib/paster_tpls/project/+package+/commands.py
pysapp/lib/paster_tpls/project/+package+/settings.py_tmpl
pysapp/lib/paster_tpls/project/+package+/site_settings.py_tmpl
pysapp/lib/paster_tpls/project/+package+/modules/__init__.py
pysapp/lib/paster_tpls/project/+package+/modules/default/__init__.py
pysapp/lib/paster_tpls/project/+package+/modules/default/actions.py
pysapp/lib/paster_tpls/project/+package+/modules/default/commands.py
pysapp/lib/paster_tpls/project/+package+/modules/default/forms.py
pysapp/lib/paster_tpls/project/+package+/modules/default/settings.py
pysapp/lib/paster_tpls/project/+package+/modules/default/utils.py
pysapp/lib/paster_tpls/project/+package+/modules/default/views.py
pysapp/lib/paster_tpls/project/+package+/modules/default/templates/Index.html
pysapp/lib/paster_tpls/project/+package+/modules/default/tests/__init__.py
