Metadata-Version: 1.0
Name: pysapp
Version: 0.2
Summary: A pysmvt supporting application
Home-page: http://pypi.python.org/pypi/pysapp/
Author: Randy Syring
Author-email: rsyring@gmail.com
License: BSD
Platform: UNKNOWN
Classifier: Development Status :: 4 - Beta
Classifier: Intended Audience :: Developers
Classifier: License :: OSI Approved :: BSD License
